thefittest/__init__.py
thefittest/base/__init__.py
thefittest/base/_ea.py
thefittest/base/_gp.py
thefittest/base/_gpnn.py
thefittest/base/_mlp.py
thefittest/base/_net.py
thefittest/base/_tree.py
thefittest/benchmarks/CEC2005.py
thefittest/benchmarks/__init__.py
thefittest/benchmarks/_datasets.py
thefittest/benchmarks/_optproblems.py
thefittest/benchmarks/symbolicregression17.py
thefittest/benchmarks/_data/EF8F2_func_data.txt
thefittest/benchmarks/_data/E_ScafferF6_M_D10.txt
thefittest/benchmarks/_data/E_ScafferF6_M_D2.txt
thefittest/benchmarks/_data/E_ScafferF6_M_D30.txt
thefittest/benchmarks/_data/E_ScafferF6_M_D50.txt
thefittest/benchmarks/_data/E_ScafferF6_func_data.txt
thefittest/benchmarks/_data/ackley_M_D10.txt
thefittest/benchmarks/_data/ackley_M_D2.txt
thefittest/benchmarks/_data/ackley_M_D30.txt
thefittest/benchmarks/_data/ackley_M_D50.txt
thefittest/benchmarks/_data/ackley_func_data.txt
thefittest/benchmarks/_data/banknote_dataset.txt
thefittest/benchmarks/_data/breast_cancer_data.txt
thefittest/benchmarks/_data/credit_risk_data.txt
thefittest/benchmarks/_data/elliptic_M_D10.txt
thefittest/benchmarks/_data/elliptic_M_D2.txt
thefittest/benchmarks/_data/elliptic_M_D30.txt
thefittest/benchmarks/_data/elliptic_M_D50.txt
thefittest/benchmarks/_data/fbias_data.txt
thefittest/benchmarks/_data/griewank_M_D10.txt
thefittest/benchmarks/_data/griewank_M_D2.txt
thefittest/benchmarks/_data/griewank_M_D30.txt
thefittest/benchmarks/_data/griewank_M_D50.txt
thefittest/benchmarks/_data/griewank_func_data.txt
thefittest/benchmarks/_data/handwritten_digits_data.txt
thefittest/benchmarks/_data/high_cond_elliptic_rot_data.txt
thefittest/benchmarks/_data/hybrid_func1_M_D10.txt
thefittest/benchmarks/_data/hybrid_func1_M_D2.txt
thefittest/benchmarks/_data/hybrid_func1_M_D30.txt
thefittest/benchmarks/_data/hybrid_func1_M_D50.txt
thefittest/benchmarks/_data/hybrid_func1_data.txt
thefittest/benchmarks/_data/hybrid_func2_M_D10.txt
thefittest/benchmarks/_data/hybrid_func2_M_D2.txt
thefittest-0.2.7.dist-info/licenses/LICENSE
thefittest-0.2.7.dist-info/licenses/NOTICE
thefittest-0.2.7.dist-info/METADATA
thefittest-0.2.7.dist-info/WHEEL
thefittest-0.2.7.dist-info/top_level.txt
thefittest-0.2.7.dist-info/RECORD
