Metadata-Version: 2.4
Name: thefittest
Version: 0.2.7
Summary: Implementation of data mining methods that use evolutionary algorithms
Author-email: Pavel Sherstnev <sherstpasha99@gmail.com>
License: MIT License
Project-URL: Homepage, https://github.com/sherstpasha/thefittest
Classifier: Programming Language :: Python :: 3
Classifier: License :: OSI Approved :: MIT License
Classifier: Operating System :: OS Independent
Requires-Python: <=3.13,>=3.7
License-File: LICENSE
License-File: NOTICE
Requires-Dist: numpy<2.0,>=1.23
Requires-Dist: numba
Requires-Dist: scipy
Requires-Dist: scikit-learn>=1.4
Requires-Dist: torch>=2.0
Requires-Dist: joblib==1.2.0
Dynamic: license-file
